{"2026-06-20T16:02": {"timestamp": 1781971349791, "status": 200, "online_count": 4}, "2026-06-20T17:45": {"timestamp": 1781977507685, "status": 200, "online_count": 2}, "2026-06-20T19:01": {"timestamp": 1781982118117, "status": 200, "online_count": 1}, "2026-06-20T20:39": {"timestamp": 1781987996139, "status": 200, "online_count": 1}, "2026-06-20T21:54": {"timestamp": 1781992491488, "status": 200, "online_count": 1}, "2026-06-20T23:16": {"timestamp": 1781997407915, "status": 200, "online_count": 0}, "2026-06-21T01:42": {"timestamp": 1782006167819, "status": 200, "online_count": 2}, "2026-06-21T06:38": {"timestamp": 1782023893743, "status": 200, "online_count": 10}, "2026-06-21T10:21": {"timestamp": 1782037271472, "status": 200, "online_count": 8}, "2026-06-21T12:25": {"timestamp": 1782044747511, "status": 200, "online_count": 9}, "2026-06-21T14:57": {"timestamp": 1782053826558, "status": 200, "online_count": 6}, "2026-06-21T16:51": {"timestamp": 1782060676002, "status": 200, "online_count": 3}, "2026-06-21T18:22": {"timestamp": 1782066140757, "status": 200, "online_count": 2}, "2026-06-21T20:13": {"timestamp": 1782072804712, "status": 200, "online_count": 0}, "2026-06-21T21:46": {"timestamp": 1782078374427, "status": 200, "online_count": 0}, "2026-06-21T22:53": {"timestamp": 1782082436725, "status": 200, "online_count": 0}, "2026-06-22T00:17": {"timestamp": 1782087459113, "status": 200, "online_count": 0}, "2026-06-22T05:36": {"timestamp": 1782106582464, "status": 200, "online_count": 3}, "2026-06-22T11:20": {"timestamp": 1782127222106, "status": 200, "online_count": 6}, "2026-06-22T16:12": {"timestamp": 1782144732322, "status": 200, "online_count": 6}, "2026-06-22T19:49": {"timestamp": 1782157795583, "status": 200, "online_count": 3}, "2026-06-22T21:56": {"timestamp": 1782165402771, "status": 200, "online_count": 1}, "2026-06-22T23:38": {"timestamp": 1782171529493, "status": 200, "online_count": 1}, "2026-06-23T01:34": {"timestamp": 1782178456551, "status": 200, "online_count": 1}, "2026-06-23T05:50": {"timestamp": 1782193831256, "status": 200, "online_count": 7}, "2026-06-23T09:57": {"timestamp": 1782208623181, "status": 200, "online_count": 7}, "2026-06-23T12:41": {"timestamp": 1782218516017, "status": 200, "online_count": 7}, "2026-06-23T15:40": {"timestamp": 1782229254973, "status": 200, "online_count": 8}, "2026-06-23T17:31": {"timestamp": 1782235886673, "status": 200, "online_count": 5}, "2026-06-23T19:30": {"timestamp": 1782243048450, "status": 200, "online_count": 1}, "2026-06-23T21:18": {"timestamp": 1782249530243, "status": 200, "online_count": 2}, "2026-06-23T22:42": {"timestamp": 1782254577048, "status": 200, "online_count": 3}, "2026-06-23T23:43": {"timestamp": 1782258201752, "status": 200, "online_count": 1}, "2026-06-24T01:48": {"timestamp": 1782265696558, "status": 200, "online_count": 2}, "2026-06-24T05:56": {"timestamp": 1782280595395, "status": 200, "online_count": 5}, "2026-06-24T09:46": {"timestamp": 1782294416423, "status": 200, "online_count": 12}, "2026-06-24T12:10": {"timestamp": 1782303039638, "status": 200, "online_count": 17}, "2026-06-24T15:12": {"timestamp": 1782313976784, "status": 200, "online_count": 12}, "2026-06-24T17:22": {"timestamp": 1782321732615, "status": 200, "online_count": 3}, "2026-06-24T19:13": {"timestamp": 1782328415547, "status": 200, "online_count": 2}, "2026-06-24T21:00": {"timestamp": 1782334849065, "status": 200, "online_count": 2}, "2026-06-24T22:38": {"timestamp": 1782340722975, "status": 200, "online_count": 1}, "2026-06-24T23:49": {"timestamp": 1782344962540, "status": 200, "online_count": 1}, "2026-06-25T02:31": {"timestamp": 1782354670779, "status": 200, "online_count": 6}, "2026-06-25T06:34": {"timestamp": 1782369248442, "status": 200, "online_count": 9}, "2026-06-25T09:56": {"timestamp": 1782381407209, "status": 200, "online_count": 9}, "2026-06-25T12:28": {"timestamp": 1782390538705, "status": 200, "online_count": 13}, "2026-06-25T15:29": {"timestamp": 1782401343375, "status": 200, "online_count": 8}, "2026-06-25T17:32": {"timestamp": 1782408738556, "status": 200, "online_count": 5}, "2026-06-25T19:29": {"timestamp": 1782415746807, "status": 200, "online_count": 1}, "2026-06-25T21:15": {"timestamp": 1782422133542, "status": 200, "online_count": 1}, "2026-06-25T22:51": {"timestamp": 1782427912852, "status": 200, "online_count": 0}, "2026-06-26T00:16": {"timestamp": 1782433013811, "status": 200, "online_count": 0}, "2026-06-26T04:45": {"timestamp": 1782449144698, "status": 200, "online_count": 8}, "2026-06-26T08:22": {"timestamp": 1782462158547, "status": 200, "online_count": 5}, "2026-06-26T11:25": {"timestamp": 1782473134339, "status": 200, "online_count": 6}, "2026-06-26T13:32": {"timestamp": 1782480745075, "status": 200, "online_count": 9}, "2026-06-26T15:58": {"timestamp": 1782489521717, "status": 200, "online_count": 6}, "2026-06-26T17:59": {"timestamp": 1782496796674, "status": 200, "online_count": 3}, "2026-06-26T20:04": {"timestamp": 1782504260489, "status": 200, "online_count": 3}, "2026-06-26T21:39": {"timestamp": 1782509941406, "status": 200, "online_count": 2}, "2026-06-26T22:51": {"timestamp": 1782514276641, "status": 200, "online_count": 3}, "2026-06-27T00:15": {"timestamp": 1782519345651, "status": 200, "online_count": 3}, "2026-06-27T04:29": {"timestamp": 1782534565540, "status": 200, "online_count": 8}, "2026-06-27T07:37": {"timestamp": 1782545821586, "status": 200, "online_count": 5}, "2026-06-27T09:50": {"timestamp": 1782553831241, "status": 200, "online_count": 6}, "2026-06-27T11:40": {"timestamp": 1782560433166, "status": 200, "online_count": 11}, "2026-06-27T12:59": {"timestamp": 1782565165133, "status": 200, "online_count": 10}, "2026-06-27T14:51": {"timestamp": 1782571904556, "status": 200, "online_count": 15}}